omero_gallery/__init__.py
omero_gallery/apps.py
omero_gallery/gallery_settings.py
omero_gallery/settings.py
omero_gallery/urls.py
omero_gallery/views.py
omero_gallery/static/gallery/categories.js
omero_gallery/static/gallery/model.js
omero_gallery/static/gallery/search.js
omero_gallery/static/gallery/studies.css
omero_gallery/static/gallery/3rdparty/bootstrap-3.1.1/css/bootstrap-theme.css
omero_gallery/static/gallery/3rdparty/bootstrap-3.1.1/css/bootstrap-theme.css.map
omero_gallery/static/gallery/3rdparty/bootstrap-3.1.1/css/bootstrap-theme.min.css
omero_gallery/static/gallery/3rdparty/bootstrap-3.1.1/css/bootstrap.css
omero_gallery/static/gallery/3rdparty/bootstrap-3.1.1/css/bootstrap.css.map
omero_gallery/static/gallery/3rdparty/bootstrap-3.1.1/css/bootstrap.min.css
omero_gallery/static/gallery/3rdparty/bootstrap-3.1.1/fonts/glyphicons-halflings-regular.eot
omero_gallery/static/gallery/3rdparty/bootstrap-3.1.1/fonts/glyphicons-halflings-regular.svg
omero_gallery/static/gallery/3rdparty/bootstrap-3.1.1/fonts/glyphicons-halflings-regular.ttf
omero_gallery/static/gallery/3rdparty/bootstrap-3.1.1/fonts/glyphicons-halflings-regular.woff
omero_gallery/static/gallery/3rdparty/bootstrap-3.1.1/js/bootstrap.js
omero_gallery/static/gallery/3rdparty/bootstrap-3.1.1/js/bootstrap.min.js
omero_gallery/static/gallery/3rdparty/foundation/foundation.min.css
omero_gallery/static/gallery/3rdparty/foundation/foundation.min.js
omero_gallery/static/gallery/css/idr.css
omero_gallery/static/gallery/css/openmicroscopy.css
omero_gallery/static/gallery/images/favicon.ico
omero_gallery/static/gallery/images/omero.svg
omero_gallery/static/gallery/images/transparent.png
omero_gallery/templates/webgallery/dataset_thumbs.html
omero_gallery/templates/webgallery/index.html
omero_gallery/templates/webgallery/show_dataset.html
omero_gallery/templates/webgallery/show_group.html
omero_gallery/templates/webgallery/show_image.html
omero_gallery/templates/webgallery/show_project.html
omero_gallery-3.4.3.dist-info/LICENSE
omero_gallery-3.4.3.dist-info/METADATA
omero_gallery-3.4.3.dist-info/WHEEL
omero_gallery-3.4.3.dist-info/top_level.txt
omero_gallery-3.4.3.dist-info/RECORD
